test_style_checker/__init__.py
test_style_checker/err.py
test_style_checker-0.1.6.dist-info/LICENSE
test_style_checker-0.1.6.dist-info/METADATA
test_style_checker-0.1.6.dist-info/WHEEL
test_style_checker-0.1.6.dist-info/entry_points.txt
test_style_checker-0.1.6.dist-info/top_level.txt
test_style_checker-0.1.6.dist-info/RECORD
